dreamhostapi/__init__.py
dreamhostapi/api.py
dreamhostapi/exceptions.py
dreamhostapi/interactiveapi.py
dreamhostapi/module.py
dreamhostapi-0.1.0.dist-info/DESCRIPTION.rst
dreamhostapi-0.1.0.dist-info/METADATA
dreamhostapi-0.1.0.dist-info/metadata.json
dreamhostapi-0.1.0.dist-info/RECORD
dreamhostapi-0.1.0.dist-info/top_level.txt
dreamhostapi-0.1.0.dist-info/WHEEL
