Metadata-Version: 2.0
Name: dreamhostapi
Version: 0.1.0
Summary: A Python wrapper around DreamHost's API
Home-page: https://github.com/mcgid/python-dreamhostapi
Author: mcgid
Author-email: dan@mcgid.ca
License: MIT
Keywords: DreamHost API interaction wrapper
Platform: UNKNOWN
Classifier: Development Status :: 4 - Beta
Classifier: Intended Audience :: Developers
Classifier: License :: OSI Approved :: MIT License
Classifier: Operating System :: OS Independent
Classifier: Programming Language :: Python :: 2.7
Classifier: Topic :: Software Development :: Libraries :: Python Modules
Requires-Dist: requests
